polars_can_parser-0.0.1.dist-info/METADATA
polars_can_parser-0.0.1.dist-info/WHEEL
polars_can_parser/__init__.py
polars_can_parser/utils.py
polars_can_parser/polars_can_parser.abi3.so
polars_can_parser-0.0.1.dist-info/RECORD
